{"pageProps":{"articolo":{"title":"Prezzo energia in aumento: quanto pagheremo le bollette di luce e gas nei prossimi mesi - PGCasa","slug":"prezzo-energia-in-aumento-quanto-pagheremo-le-bollette-di-luce-e-gas-nei-prossim","date":"2026-04-08","nicchia":"energia","nicchia_nome":"Energia & Bollette","meta_description":"Prezzo energia in aumento: quanto pagheremo le bollette di luce e gas nei prossimi mesi - PGCasa","tags":["bolletta luce","gas","fotovoltaico"],"auto_generated":true,"contenuto":"<h1>Bolletta Luce e Gas in Aumento: Quanto Pagheremo nei Prossimi Mesi del 2026</h1>\n<p>L'inizio della primavera 2026 porta con sé una notizia che riguarda direttamente le tasche degli italiani: i prezzi dell'energia sono in aumento. Dopo un periodo di relativa stabilità, i costi della bolletta luce e del gas tornano a salire, modificando gli equilibri dei bilanci familiari e aziendali. Secondo le ultime analisi del mercato energetico, questa tendenza continuerà nei prossimi mesi, con incrementi che potrebbero interessare sia i clienti del mercato libero che quelli in tutela.</p>\n<p>In questo articolo analizziamo le cause di questo rincaro energetico, le previsioni per i prossimi mesi e soprattutto quali soluzioni alternative possono aiutare i consumatori a contenere i costi, dal fotovoltaico alle strategie di risparmio energetico.</p>\n<h2>Perché la Bolletta Luce Aumenta nel 2026</h2>\n<p>I motivi dietro questo incremento dei prezzi energetici sono molteplici e interconnessi. In primo luogo, le tensioni geopolitiche internazionali continuano a influenzare le quotazioni del gas naturale sui mercati mondiali, spingendo al rialzo i costi per i fornitori italiani. Il prezzo del gas, infatti, rimane uno dei principali driver che determina l'andamento delle tariffe energetiche nel nostro Paese.</p>\n<p>Inoltre, la domanda di energia rimane elevata, specialmente dopo l'incremento dei consumi legato all'espansione economica che caratterizza il 2026. Le aziende aumentano la produzione, e anche i consumi domestici salgono con l'arrivo della stagione più calda, quando cresce l'utilizzo dei sistemi di climatizzazione.</p>\n<p>Un altro fattore rilevante riguarda gli investimenti infrastrutturali e la manutenzione delle reti di distribuzione: i gestori devono effettuare interventi significativi per modernizzare gli impianti e garantire maggiore resilienza e efficienza, costi che vengono trasferiti sulla bolletta luce attraverso le componenti tariffarie.</p>\n<h2>Quanto Aumenteranno le Bollette nei Prossimi Mesi</h2>\n<p>Le previsioni per il secondo e terzo trimestre del 2026 indicano un aumento medio della bolletta luce che potrebbe oscillare tra il 5% e l'8%, a seconda del gestore e della zona geografica di fornitura. Per una famiglia media con consumi stimati attorno ai 3.000 kWh annui, questo si traduce in un incremento di circa 100-150 euro all'anno rispetto ai valori attuali di aprile 2026.</p>\n<p>Per quanto riguarda il gas, gli aumenti potrebbero risultare ancora più significativi, con rincari che vanno dal 7% al 12%, soprattutto considerando che i consumi invernali richiedono maggiore attenzione durante i mesi autunnali e invernali. Una famiglia che consuma 800-1.000 metri cubi di gas all'anno potrebbe vedersi aumentata la bolletta di 150-250 euro nei prossimi mesi.</p>\n<p>È importante notare che questi aumenti si applicano principalmente ai clienti in regime di tutela e a coloro che hanno sottoscritto contratti con clausole indicizzate. I clienti del mercato libero con contratti fissi per il 2026 potranno contare su una maggiore stabilità tariffaria fino alla scadenza della loro fornitura.</p>\n<h2>Il Fotovoltaico Come Soluzione Strutturale</h2>\n<p>Di fronte a questa dinamica rialzista dei prezzi energetici, molti consumatori italiani stanno considerando seriamente l'installazione di impianti fotovoltaici come risposta concreta. Nel 2026, le tecnologie solari sono diventate ancora più competitive e affidabili, con costi di installazione in calo rispetto agli anni precedenti.</p>\n<p>Un impianto fotovoltaico residenziale di media dimensione (5-6 kW) consente di coprire circa il 50-70% dei consumi annui di una famiglia tipo, producendo un beneficio economico notevole attraverso l'autoconsumo e lo scambio sulla rete. Con i meccanismi di incentivo statale ancora attivi nel 2026, l'investimento iniziale risulta ammortizzabile in 6-8 anni di esercizio.</p>\n<p><strong>Vantaggi principali del fotovoltaico nel 2026:</strong></p>\n<ul>\n<li>Riduzione della bolletta luce fino al 70%</li>\n<li>Protezione dall'inflazione energetica futura</li>\n<li>Possibilità di accumulo con batterie (sempre più convenienti economicamente)</li>\n<li>Aumentato valore dell'immobile</li>\n<li>Contributo concreto alla sostenibilità ambientale</li>\n<li>Accesso a detrazioni fiscali e bonus energetici</li>\n</ul>\n<p>Inoltre, le batterie di accumulo, inizialmente un costo aggiuntivo, diventano sempre più interessanti dal punto di vista economico, permettendo di immagazzinare l'energia prodotta durante il giorno per utilizzarla nelle ore serali, quando i prezzi orari (nel mercato libero) tendono ad essere più elevati.</p>\n<h2>Strategie per Contenere i Costi della Bolletta nel 2026</h2>\n<p>Se l'installazione di un impianto fotovoltaico non è al momento possibile, esistono diverse strategie per ridurre l'impatto degli aumenti sulla bolletta luce e gas:</p>\n<p><strong>Comportamenti virtuosi e piccoli interventi:</strong></p>\n<ul>\n<li>Sostituire le lampadine tradizionali con LED (consumano fino all'80% meno energia)</li>\n<li>Spegnere i dispositivi in standby e utilizzare ciabatte con interruttore</li>\n<li>Migliorare l'isolamento termico di finestre e porte</li>\n<li>Regolare gli impianti di riscaldamento e raffreddamento a temperature moderate</li>\n<li>Eseguire una corretta manutenzione dei condizionatori e delle caldaie</li>\n<li>Scegliere elettrodomestici con classe energetica A o superiore</li>\n</ul>\n<p><strong>Scelte commerciali:</strong></p>\n<ul>\n<li>Confrontare le offerte dei diversi fornitori di energia</li>\n<li>Valutare l'opportunità di cambiare gestore se le condizioni sono più vantaggiose</li>\n<li>Negoziare le tariffe se cliente business</li>\n<li>Optare per contratti con prezzo fisso quando le condizioni di mercato lo consentono</li>\n</ul>\n<h2>Cosa Aspettarsi Nei Prossimi Trimestri del 2026</h2>\n<p>Le proiezioni degli analisti del mercato energetico per il periodo aprile-dicembre 2026 suggeriscono una graduale stabilizzazione dopo i picchi primaverili. Tuttavia, non è escluso che fattori geopolitici imprevisti possano alterare questo scenario, soprattutto per quanto riguarda le quotazioni del gas naturale.</p>\n<p>Per i consumi estivi, è prevedibile una riduzione della componente gas e un aumento leggermente più marcato per l'energia elettrica, dovuta all'incremento dei consumi di raffreddamento. A partire dall'autunno 2026, il rialzo dei consumi di riscaldamento tornerà a pressare sui costi del gas.</p>\n<h2>Conclusione</h2>\n<p>Gli aumenti della bolletta luce e gas nel 2026 rappresentano una sfida concreta per le finanze domestiche, ma anche un'opportunità per ripensare il proprio consumo energetico. Che si tratti di investire in un fotovoltaico, di adottare comportamenti più efficienti o di negoziare con il fornitore, le azioni disponibili per contenere l'impatto economico non mancano. La chiave è agire consapevolmente e tempestivamente, sfruttando gli incentivi ancora disponibili e le tecnologie oggi mature per garantirsi una maggiore indipendenza energetica e una protezione contro l'inflazione del prezzo dell'energia nei mesi e anni a venire.</p>\n"}},"__N_SSG":true}